[
{
    "title": "Project 1",
    "description": "This is my first project!",
    "image": "./project-images/gatsby-astronaut.png",
    "url": "https://example.com",
    "slug": "/projects/projectone",
    "author": "Keelan Jonathan",
    "category": "Web Development"
},
{
    "title": "Project 2",
    "description": "This is my second project!",
    "image": "./project-images/gatsby-astronaut.png",
    "url": "https://example.com",
    "slug": "project-two",
    "author": "Keelan Jonathan",
    "category": "Web Development"
},
{
    "title": "Lets Talk Ments Mental Health",
    "description": "A website design and development project",
    "image": "./project-images/gatsby-astronaut.png",
    "url": "https://letstalk.org.uk",
    "slug": "/projects/letstalk-project/",
    "author": "Keelan Jonathan",
    "category": "Web Design, Web Development"
}
,
{
    "title": "Project 4",
    "description": "This is my fourth project!",
    "image": "./project-images/gatsby-astronaut.png",
    "url": "https://example.com",
    "slug": "project-four",
    "author": "Keelan Jonathan",
    "category": "Web Development"
}
]
